setup.py
cyberchase/__init__.py
cyberchase/__main__.py
cyberchase/board.py
cyberchase/game.py
cyberchase/hider.py
cyberchase/match.py
cyberchase/seeker.py
cyberchase.egg-info/PKG-INFO
cyberchase.egg-info/SOURCES.txt
cyberchase.egg-info/dependency_links.txt
cyberchase.egg-info/requires.txt
cyberchase.egg-info/top_level.txt